pyoptree/__init__.py
pyoptree/example.py
pyoptree/localsearch.py
pyoptree/naivecart.py
pyoptree/optree.py
pyoptree/tree.py
pyoptree-1.0.3.dist-info/METADATA
pyoptree-1.0.3.dist-info/RECORD
pyoptree-1.0.3.dist-info/WHEEL
pyoptree-1.0.3.dist-info/top_level.txt
