Metadata-Version: 2.1
Name: pyoptree
Version: 1.0.3
Summary: Python Implementation of Bertsimas's paper Optimal Classification Trees.
Home-page: https://github.com/pan5431333/pyoptree
Author: Meng Pan
Author-email: meng.pan95@gmail.com
Maintainer: Meng Pan
Maintainer-email: meng.pan95@gmail.com
License: BSD License
Platform: all
Classifier: Development Status :: 4 - Beta
Classifier: Operating System :: OS Independent
Classifier: Intended Audience :: Developers
Classifier: License :: OSI Approved :: BSD License
Classifier: Programming Language :: Python :: 3
Classifier: Programming Language :: Python :: 3.4
Classifier: Programming Language :: Python :: 3.5
Classifier: Programming Language :: Python :: 3.6
Classifier: Topic :: Software Development :: Libraries
Requires-Dist: numpy (>=1.14.5)
Requires-Dist: pandas (>=0.23.1)
Requires-Dist: pyomo (>=5.5.0)
Requires-Dist: scikit-learn (>=0.20.0)
Requires-Dist: tqdm (>=4.26.0)
